{
  "title": "Mufradot — 1-dars: At-Taoruf (Tanishuv)",
  "otish": 70,
  "vaqt": 19,
  "questions": [
    {
      "q": "«اَلسَّلَامُ عَلَيْكُمْ» so'zining ma'nosi?",
      "opts": [
        "Assalomu alaykum",
        "Daftar",
        "Arzimaydi",
        "Salomat bo'ling"
      ],
      "correct": 0,
      "izoh": "اَلسَّلَامُ عَلَيْكُمْ = Assalomu alaykum."
    },
    {
      "q": "«وَعَلَيْكُمُ السَّلَامُ» so'zining ma'nosi?",
      "opts": [
        "Vaalaykum assalom",
        "Arzimaydi",
        "Men",
        "Talaba"
      ],
      "correct": 0,
      "izoh": "وَعَلَيْكُمُ السَّلَامُ = Vaalaykum assalom."
    },
    {
      "q": "«كَيْفَ حَالُكَ؟» so'zining ma'nosi?",
      "opts": [
        "Ahvolingiz qanday?",
        "Rahmat",
        "Arzimaydi",
        "Sen"
      ],
      "correct": 0,
      "izoh": "كَيْفَ حَالُكَ؟ = Ahvolingiz qanday?."
    },
    {
      "q": "«بِخَيْرٍ وَالْحَمْدُ لِلَّهِ» so'zining ma'nosi?",
      "opts": [
        "Yaxshi, Allohga shukr",
        "Kim",
        "Bu",
        "Assalomu alaykum"
      ],
      "correct": 0,
      "izoh": "بِخَيْرٍ وَالْحَمْدُ لِلَّهِ = Yaxshi, Allohga shukr."
    },
    {
      "q": "«مَا اسْمُكَ؟» so'zining ma'nosi?",
      "opts": [
        "Ismingiz nima?",
        "U (erkak)",
        "Daftar",
        "Ko'rishguncha"
      ],
      "correct": 0,
      "izoh": "مَا اسْمُكَ؟ = Ismingiz nima?."
    },
    {
      "q": "«مِنْ أَيْنَ أَنْتَ؟» so'zining ma'nosi?",
      "opts": [
        "Qayerdansiz?",
        "Daftar",
        "Qalam",
        "O'qituvchi"
      ],
      "correct": 0,
      "izoh": "مِنْ أَيْنَ أَنْتَ؟ = Qayerdansiz?."
    },
    {
      "q": "«أَهْلًا وَسَهْلًا» so'zining ma'nosi?",
      "opts": [
        "Xush kelibsiz",
        "Shifokor",
        "Ham",
        "Ismingiz nima?"
      ],
      "correct": 0,
      "izoh": "أَهْلًا وَسَهْلًا = Xush kelibsiz."
    },
    {
      "q": "«تَشَرَّفْتُ» so'zining ma'nosi?",
      "opts": [
        "Tanishganimdan xursandman",
        "Daftar",
        "Xayrli tong",
        "Ahvolingiz qanday?"
      ],
      "correct": 0,
      "izoh": "تَشَرَّفْتُ = Tanishganimdan xursandman."
    },
    {
      "q": "«صَبَاحُ الْخَيْرِ» so'zining ma'nosi?",
      "opts": [
        "Xayrli tong",
        "Ham",
        "Assalomu alaykum",
        "Rahmat"
      ],
      "correct": 0,
      "izoh": "صَبَاحُ الْخَيْرِ = Xayrli tong."
    },
    {
      "q": "«مَسَاءُ الْخَيْرِ» so'zining ma'nosi?",
      "opts": [
        "Xayrli kech",
        "Xayrli tong",
        "Rahmat",
        "Ham"
      ],
      "correct": 0,
      "izoh": "مَسَاءُ الْخَيْرِ = Xayrli kech."
    },
    {
      "q": "«إِلَى اللِّقَاءِ» so'zining ma'nosi?",
      "opts": [
        "Ko'rishguncha",
        "O'qituvchi",
        "Ham",
        "U (erkak)"
      ],
      "correct": 0,
      "izoh": "إِلَى اللِّقَاءِ = Ko'rishguncha."
    },
    {
      "q": "«مَعَ السَّلَامَةِ» so'zining ma'nosi?",
      "opts": [
        "Salomat bo'ling",
        "Bu",
        "Ko'rishguncha",
        "Xayrli tong"
      ],
      "correct": 0,
      "izoh": "مَعَ السَّلَامَةِ = Salomat bo'ling."
    },
    {
      "q": "«نَعَمْ» so'zining ma'nosi?",
      "opts": [
        "Ha",
        "Bu",
        "Qayerdansiz?",
        "Rahmat"
      ],
      "correct": 0,
      "izoh": "نَعَمْ = Ha."
    },
    {
      "q": "«لَا» so'zining ma'nosi?",
      "opts": [
        "Yo'q",
        "U (erkak)",
        "Ha",
        "Tanishganimdan xursandman"
      ],
      "correct": 0,
      "izoh": "لَا = Yo'q."
    },
    {
      "q": "«شُكْرًا» so'zining ma'nosi?",
      "opts": [
        "Rahmat",
        "Ha",
        "O'qituvchi",
        "Yaxshi, Allohga shukr"
      ],
      "correct": 0,
      "izoh": "شُكْرًا = Rahmat."
    },
    {
      "q": "«عَفْوًا» so'zining ma'nosi?",
      "opts": [
        "Arzimaydi",
        "O'qituvchi",
        "Talaba",
        "Kim"
      ],
      "correct": 0,
      "izoh": "عَفْوًا = Arzimaydi."
    },
    {
      "q": "«طَالِبٌ» so'zining ma'nosi?",
      "opts": [
        "Talaba",
        "Daftar",
        "Yaxshi, Allohga shukr",
        "Ham"
      ],
      "correct": 0,
      "izoh": "طَالِبٌ = Talaba."
    },
    {
      "q": "«مُعَلِّمٌ» so'zining ma'nosi?",
      "opts": [
        "O'qituvchi",
        "Arzimaydi",
        "Tanishganimdan xursandman",
        "Xayrli kech"
      ],
      "correct": 0,
      "izoh": "مُعَلِّمٌ = O'qituvchi."
    },
    {
      "q": "«كِتَابٌ» so'zining ma'nosi?",
      "opts": [
        "Kitob",
        "Tanishganimdan xursandman",
        "Rahmat",
        "Qayerdansiz?"
      ],
      "correct": 0,
      "izoh": "كِتَابٌ = Kitob."
    },
    {
      "q": "«قَلَمٌ» so'zining ma'nosi?",
      "opts": [
        "Qalam",
        "...mi? (savol yuklamasi)",
        "Ham",
        "Vaalaykum assalom"
      ],
      "correct": 0,
      "izoh": "قَلَمٌ = Qalam."
    },
    {
      "q": "«دَفْتَرٌ» so'zining ma'nosi?",
      "opts": [
        "Daftar",
        "Bu",
        "Salomat bo'ling",
        "Xayrli kech"
      ],
      "correct": 0,
      "izoh": "دَفْتَرٌ = Daftar."
    },
    {
      "q": "«طَبِيبٌ» so'zining ma'nosi?",
      "opts": [
        "Shifokor",
        "Ham",
        "Assalomu alaykum",
        "Qalam"
      ],
      "correct": 0,
      "izoh": "طَبِيبٌ = Shifokor."
    },
    {
      "q": "«صُورَةٌ» so'zining ma'nosi?",
      "opts": [
        "Surat",
        "Salomat bo'ling",
        "Kitob",
        "Arzimaydi"
      ],
      "correct": 0,
      "izoh": "صُورَةٌ = Surat."
    },
    {
      "q": "«أَيْضًا» so'zining ma'nosi?",
      "opts": [
        "Ham",
        "Xayrli tong",
        "Surat",
        "Yo'q"
      ],
      "correct": 0,
      "izoh": "أَيْضًا = Ham."
    },
    {
      "q": "«أَنَا» so'zining ma'nosi?",
      "opts": [
        "Men",
        "Qayerdansiz?",
        "Ismingiz nima?",
        "Talaba"
      ],
      "correct": 0,
      "izoh": "أَنَا = Men."
    },
    {
      "q": "«أَنْتَ» so'zining ma'nosi?",
      "opts": [
        "Sen",
        "...mi? (savol yuklamasi)",
        "Ko'rishguncha",
        "Ahvolingiz qanday?"
      ],
      "correct": 0,
      "izoh": "أَنْتَ = Sen."
    },
    {
      "q": "«هُوَ» so'zining ma'nosi?",
      "opts": [
        "U (erkak)",
        "Surat",
        "Xayrli tong",
        "Vaalaykum assalom"
      ],
      "correct": 0,
      "izoh": "هُوَ = U (erkak)."
    },
    {
      "q": "«هَذَا» so'zining ma'nosi?",
      "opts": [
        "Bu",
        "Vaalaykum assalom",
        "O'qituvchi",
        "Salomat bo'ling"
      ],
      "correct": 0,
      "izoh": "هَذَا = Bu."
    },
    {
      "q": "«هَلْ» so'zining ma'nosi?",
      "opts": [
        "...mi? (savol yuklamasi)",
        "Men",
        "Vaalaykum assalom",
        "Xayrli tong"
      ],
      "correct": 0,
      "izoh": "هَلْ = ...mi? (savol yuklamasi)."
    },
    {
      "q": "«مَنْ» so'zining ma'nosi?",
      "opts": [
        "Kim",
        "Daftar",
        "Assalomu alaykum",
        "Qalam"
      ],
      "correct": 0,
      "izoh": "مَنْ = Kim."
    },
    {
      "q": "«مَا» so'zining ma'nosi?",
      "opts": [
        "Nima",
        "Bu",
        "Ko'rishguncha",
        "Salomat bo'ling"
      ],
      "correct": 0,
      "izoh": "مَا = Nima."
    }
  ]
}