{
  "title": "Istima — A2 6-dars: Sog'lom va zararli ovqatlar",
  "audio": "a2_6_istima.mp3",
  "otish": 80,
  "vaqt": 10,
  "tinglash": 2,
  "questions": [
    {
      "q": "تَنَاوُلُ الشَّايِّ بَعْدَ الطَّعَامِ مُفِيدٌ لِلصِّحَّةِ",
      "opts": [
        "صَحِيحٌ",
        "خَطَأٌ"
      ],
      "correct": 1,
      "izoh": "Ovqatdan keyin choy ichish sog'liq uchun foydalidir — To'g'ri javob: Xato"
    },
    {
      "q": "مَنْ يَكْرَهُ الدَّوَاءَ لَا يَتَنَاوَلُ الْأَطْعِمَةَ الضَّارَّةَ",
      "opts": [
        "صَحِيحٌ",
        "خَطَأٌ"
      ],
      "correct": 0,
      "izoh": "Dorini yomon ko'rgan odam zararli taomlarni tanovul qilmaydi — To'g'ri javob: To'g'ri"
    },
    {
      "q": "الْعَصَائِرُ الْمُعَلَّبَةُ أَكْثَرُ فَائِدَةً مِنَ الْمِيَاهِ الْغَازِيَّةِ",
      "opts": [
        "صَحِيحٌ",
        "خَطَأٌ"
      ],
      "correct": 1,
      "izoh": "Qutilardagi tayyor sharbatlar gazli suvlarga qaraganda foydaliroqdir — To'g'ri javob: Xato"
    },
    {
      "q": "الْمَشْيُ بَعْدَ الطَّعَامِ مُفِيدٌ لِلصِّحَّةِ",
      "opts": [
        "صَحِيحٌ",
        "خَطَأٌ"
      ],
      "correct": 0,
      "izoh": "Ovqatdan keyin piyoda yurish sog'liq uchun foydalidir — To'g'ri javob: To'g'ri"
    },
    {
      "q": "الْأَطْعِمَةُ السَّرِيعَةُ غَيْرُ مُفِيدَةٍ، لَكِنَّهَا لَذِيذَةٌ",
      "opts": [
        "صَحِيحٌ",
        "خَطَأٌ"
      ],
      "correct": 0,
      "izoh": "Fast-fud (tezkor taomlar) foydali emas, biroq mazalidir — To'g'ri javob: To'g'ri"
    }
  ]
}