{
  "title": "Istima — B1 8-dars: الزواج في المجتمعات (Nikoh)",
  "audio": "b1_8_istima.mp3",
  "otish": 80,
  "vaqt": 10,
  "tinglash": 2,
  "questions": [
    {
      "q": "بَيْنَ مَنْ يَدُورُ الْحِوَارُ؟",
      "opts": [
        "بَيْنَ عَمَّارٍ وَنُوحٍ",
        "بَيْنَ أَحْمَدَ وَعَلِيٍّ",
        "بَيْنَ سَمِيرٍ وَخَالِدٍ",
        "بَيْنَ مَحْمُودٍ وَصَدِيقِهِ"
      ],
      "correct": 0,
      "izoh": "Suhbat Ammor va Nuh o'rtasida."
    },
    {
      "q": "لِمَاذَا اعْتَذَرَ نُوحٌ لِصَدِيقِهِ؟",
      "opts": [
        "لِأَنَّهُ لَمْ يَتَّصِلْ بِهِ مُنْذُ زَمَنٍ بِسَبَبِ انْشِغَالِهِ بِتَجْهِيزِ الزَّوَاجِ",
        "لِأَنَّهُ سَافَرَ",
        "لِأَنَّهُ كَانَ مَرِيضًا",
        "لِأَنَّهُ نَسِيَ رَقْمَهُ"
      ],
      "correct": 0,
      "izoh": "Nikoh tayyorgarligi bilan band bo'lib, aloqa qilmagani uchun."
    },
    {
      "q": "مَنْ هِيَ الزَّوْجَةُ الَّتِي وَجَدَهَا نُوحٌ؟",
      "opts": [
        "صَدِيقَةُ أُخْتِهِ وَتَعْمَلُ طَبِيبَةً",
        "جَارَتُهُ وَتَعْمَلُ مُعَلِّمَةً",
        "قَرِيبَتُهُ وَتَعْمَلُ مُهَنْدِسَةً",
        "زَمِيلَتُهُ فِي الْعَمَلِ"
      ],
      "correct": 0,
      "izoh": "Opasining dugonasi, kasbi — shifokor."
    },
    {
      "q": "مَتَى سَيَكُونُ حَفْلُ الزَّوَاجِ؟",
      "opts": [
        "يَوْمَ الْخَمِيسِ الْقَادِمِ",
        "يَوْمَ الْجُمُعَةِ",
        "بَعْدَ شَهْرٍ",
        "فِي الْعِيدِ"
      ],
      "correct": 0,
      "izoh": "Kelasi payshanba kuni."
    },
    {
      "q": "أَيْنَ سَيَكُونُ الْحَفْلُ؟",
      "opts": [
        "فِي قَاعَةِ الْأَفْرَاحِ بِالْقُرْبِ مِنْ حَيِّ الزُّهُورِ",
        "فِي بَيْتِ الْعَائِلَةِ",
        "فِي حَدِيقَةٍ عَامَّةٍ",
        "فِي مَطْعَمٍ"
      ],
      "correct": 0,
      "izoh": "Zuhur mahallasi yaqinidagi to'yxonada."
    },
    {
      "q": "آخِرُ مَرَّةٍ تَكَلَّمَ فِيهَا الصَّدِيقَانِ كَانَتْ قَبْلَ شَهْرٍ.",
      "opts": [
        "صحيح",
        "خطأ"
      ],
      "correct": 0,
      "izoh": "To'g'ri — javob: صحيح."
    },
    {
      "q": "عَمَّارٌ لَمْ يَتَزَوَّجْ مِنْ قَبْلُ.",
      "opts": [
        "صحيح",
        "خطأ"
      ],
      "correct": 1,
      "izoh": "Xato — «أنت تزوجت من قبل» — javob: خطأ."
    },
    {
      "q": "لِمَاذَا اتَّصَلَ نُوحٌ بِعَمَّارٍ؟",
      "opts": [
        "لِيَدْعُوَهُ إِلَى حَفْلِ الزَّوَاجِ",
        "لِيَطْلُبَ مِنْهُ الْمَالَ",
        "لِيُوَدِّعَهُ قَبْلَ السَّفَرِ",
        "لِيَسْأَلَهُ عَنِ الْعَمَلِ"
      ],
      "correct": 0,
      "izoh": "To'y marosimiga taklif qilish uchun."
    }
  ]
}