{
  "title": "Qovaid — B1 9-dars",
  "otish": 80,
  "vaqt": 40,
  "questions": [
    {
      "q": "Bo'sh joyga mos keladigan to'g'ri so'zni tanlang:\nيُعْمَلُ القَاضِي في الـ...........",
      "opts": [
        "الحَاكِمِ",
        "مَحْكَمَةِ",
        "الحَكَمِ",
        "الحِكْمَةِ"
      ],
      "correct": 1,
      "izoh": "Toʻgʻri javob: «مَحْكَمَةِ»."
    },
    {
      "q": "Boʻsh joyga mos soʻzni tanlang:\nهَذَا هُوَ ........... مُبَارَاةِ كُرَةِ القَدَمِ.",
      "opts": [
        "المَحْكَمَةُ",
        "الحَكَمُ",
        "الحِكْمَةُ",
        "حُكِمَ"
      ],
      "correct": 1,
      "izoh": "Toʻgʻri javob: «الحَكَمُ»."
    },
    {
      "q": "Boʻsh joyga mos soʻzni tanlang:\n........... القَاضِي بِالسِّجْنِ عَلَى السَّارِقِ.",
      "opts": [
        "حِكْمَةٌ",
        "مَحْكَمَةٌ",
        "حَاكِمٌ",
        "حَكَمَ"
      ],
      "correct": 3,
      "izoh": "Toʻgʻri javob: «حَكَمَ»."
    },
    {
      "q": "Boʻsh joyga mos soʻzni tanlang:\nهَذِهِ القِصَّةُ فِيهَا ........... جَمِيلَةٌ.",
      "opts": [
        "حَكَمَ",
        "حَاكِمٌ",
        "حِكْمَةٌ",
        "مَحْكَمَةٌ"
      ],
      "correct": 2,
      "izoh": "Toʻgʻri javob: «حِكْمَةٌ»."
    },
    {
      "q": "Boʻsh joyga mos soʻzni tanlang:\n........... المَدِينَةِ رَجُلٌ عَادِلٌ.",
      "opts": [
        "حَاكِمُ",
        "حَكَمُ",
        "حِكْمَةُ",
        "مَحْكَمَةُ"
      ],
      "correct": 0,
      "izoh": "Toʻgʻri javob: «حَاكِمُ»."
    },
    {
      "q": "Bo'sh joyga mos keladigan to'g'ri predlogni (حرف الجر) tanlang:\nنَادَى الأَبُ ........... ابْنِهِ لِيَأْكُلَ مَعَهُ الطَّعَامَ.",
      "opts": [
        "عَنْ",
        "إِلَى",
        "فِي",
        "عَلَى"
      ],
      "correct": 3,
      "izoh": "Mos harfi jar: «عَلَى»."
    },
    {
      "q": "Boʻsh joyga mos harfi jarni (predlogni) tanlang:\nاشْتَهَرَ جُحَا ........... الذَّكَاءِ وَالْمَرَحِ بَيْنَ النَّاسِ.",
      "opts": [
        "عَنْ",
        "مِنْ",
        "عَلَى",
        "بِـ"
      ],
      "correct": 3,
      "izoh": "Mos harfi jar: «بِـ»."
    },
    {
      "q": "Boʻsh joyga mos harfi jarni (predlogni) tanlang:\nبَحَثَ الطَّالِبُ ........... مَعْنَى الكَلِمَةِ فِي المُعْجَمِ.",
      "opts": [
        "بِـ",
        "عَنْ",
        "إِلَى",
        "فِي"
      ],
      "correct": 1,
      "izoh": "Mos harfi jar: «عَنْ»."
    },
    {
      "q": "Boʻsh joyga mos harfi jarni (predlogni) tanlang:\nتُنْسَبُ كَثِيرٌ مِنَ القِصَصِ ........... جُحَا وَهُوَ لَمْ يَقُلْهَا.",
      "opts": [
        "عَنْ",
        "عَلَى",
        "فِي",
        "إِلَى"
      ],
      "correct": 3,
      "izoh": "Mos harfi jar: «إِلَى»."
    },
    {
      "q": "Boʻsh joyga mos harfi jarni (predlogni) tanlang:\nعَاشَ أَشْعَبُ ........... العَصْرِ العَبَّاسِيِّ.",
      "opts": [
        "مِنْ",
        "فِي",
        "إِلَى",
        "عَلَى"
      ],
      "correct": 1,
      "izoh": "Mos harfi jar: «فِي»."
    },
    {
      "q": "Boʻsh joyga mos harfi jarni (predlogni) tanlang:\nكَثِيرٌ ........... النَّاسِ يُحِبُّونَ القِصَصَ وَالحِكَايَاتِ.",
      "opts": [
        "مِنَ",
        "إِلَى",
        "عَنْ",
        "فِي"
      ],
      "correct": 0,
      "izoh": "Mos harfi jar: «مِنَ»."
    },
    {
      "q": "Ma'noga mos keladigan to'g'ri shart yuklamasini (أداة الشرط) tanlang:\n........... تَبْتَعِدْ عَن صَدِيقِ السُّوءِ يَحْتَرِمْكَ النَّاسُ.",
      "opts": [
        "إِذَا",
        "مَنْ",
        "إِنْ",
        "لَوْ"
      ],
      "correct": 2,
      "izoh": "Toʻgʻri javob: «إِنْ»."
    },
    {
      "q": "Boʻsh joyga mos soʻzni tanlang:\n........... يَحْتَرِمْ وَالِدَيْهِ يَحْصُلْ عَلَى رِضَاهُمَا.",
      "opts": [
        "مَنْ",
        "إِذَا",
        "لَوْ",
        "إِنْ"
      ],
      "correct": 0,
      "izoh": "Toʻgʻri javob: «مَنْ»."
    },
    {
      "q": "Boʻsh joyga mos soʻzni tanlang:\n........... أَتَيْتَ غَدًا إِلَى بَيْتِنَا وَجَدْتَ خَيْرًا كَثِيرًا.",
      "opts": [
        "لَوْ",
        "مَنْ",
        "إِذَا",
        "إِنْ"
      ],
      "correct": 2,
      "izoh": "Toʻgʻri javob: «إِذَا»."
    },
    {
      "q": "Boʻsh joyga mos soʻzni tanlang:\n........... دَرَسْتَ جَيِّدًا الأُسْبُوعَ المَاضِيَ لَنَجَحْتَ.",
      "opts": [
        "لَوْ",
        "إِنْ",
        "مَنْ",
        "إِذَا"
      ],
      "correct": 0,
      "izoh": "Toʻgʻri javob: «لَوْ»."
    },
    {
      "q": "Boʻsh joyga mos soʻzni tanlang:\n........... رَأَيْتَ أَخِي فَقُلْ لَهُ: إِنِّي أُرِيدُ أَنْ يَأْتِيَ.",
      "opts": [
        "لَوْ",
        "إِذَا",
        "إِنْ",
        "مَنْ"
      ],
      "correct": 1,
      "izoh": "Toʻgʻri javob: «إِذَا»."
    },
    {
      "q": "Boʻsh joyga mos soʻzni tanlang:\n........... يَزْرَعْ خَيْرًا يَحْصُدْ خَيْرًا.",
      "opts": [
        "مَنْ",
        "لَوْ",
        "إِنْ",
        "إِذَا"
      ],
      "correct": 0,
      "izoh": "Toʻgʻri javob: «مَنْ»."
    },
    {
      "q": "Boʻsh joyga mos soʻzni tanlang:\n........... تَفْعَلْ خَيْرًا يُحْبِبْكَ النَّاسُ.",
      "opts": [
        "إِنْ",
        "لَوْ",
        "إِذَا",
        "مَنْ"
      ],
      "correct": 0,
      "izoh": "Toʻgʻri javob: «إِنْ»."
    },
    {
      "q": "Boʻsh joyga mos soʻzni tanlang:\n........... سَمِعَ اللَّاعِبُونَ كَلَامَ المُدَرِّبِ لَفَازُوا.",
      "opts": [
        "إِنْ",
        "لَوْ",
        "مَنْ",
        "إِذَا"
      ],
      "correct": 1,
      "izoh": "Toʻgʻri javob: «لَوْ»."
    },
    {
      "q": "Boʻsh joyga mos soʻzni tanlang:\nمَنْ يَشْعُرْ بِآلَامِ النَّاسِ ........... اللهُ.",
      "opts": [
        "لَمْ يُحِبَّ",
        "يُحِبَّهُ",
        "يُحِبُّ",
        "فَيُحِبُّ"
      ],
      "correct": 1,
      "izoh": "Toʻgʻri javob: «يُحِبَّهُ»."
    },
    {
      "q": "Boʻsh joyga mos soʻzni tanlang:\nإِذَا جَاءَ فَصْلُ الرَّبِيعِ ........... الأَزْهَارُ.",
      "opts": [
        "تَتَفَتَّحْ",
        "تَفَتَّحَتِ",
        "لَتَفَتَّحَتْ",
        "يَتَفَتَّحُ"
      ],
      "correct": 1,
      "izoh": "Toʻgʻri javob: «تَفَتَّحَتِ»."
    },
    {
      "q": "Boʻsh joyga mos soʻzni tanlang:\nلَوْ شَرِبْتَ دَوَاءَكَ بِانْتِظَامٍ ...........",
      "opts": [
        "فَشُفِيتَ",
        "شُفِيتَ",
        "لَشُفِيتَ",
        "تَشْفَى"
      ],
      "correct": 2,
      "izoh": "Toʻgʻri javob: «لَشُفِيتَ»."
    },
    {
      "q": "Boʻsh joyga mos soʻzni tanlang:\nإِنْ تَحْتَرِمْ وَالِدَيْكَ ........... أَبْنَاؤُكَ.",
      "opts": [
        "لَيَحْتَرِمَكَ",
        "يَحْتَرِمْكَ",
        "فَاحْتَرِمْكَ",
        "يَحْتَرِمُونَكَ"
      ],
      "correct": 1,
      "izoh": "Toʻgʻri javob: «يَحْتَرِمْكَ»."
    },
    {
      "q": "Boʻsh joyga mos soʻzni tanlang:\nإِذَا حَكَمْتَ بَيْنَ النَّاسِ ........... بِالعَدْلِ.",
      "opts": [
        "تَحْكُمْ",
        "فَاحْكُمْ",
        "لَاحْكُمْ",
        "يَحْكُمُ"
      ],
      "correct": 1,
      "izoh": "Toʻgʻri javob: «فَاحْكُمْ»."
    },
    {
      "q": "Boʻsh joyga mos soʻzni tanlang:\nمَنْ يُمَارِسِ الرِّيَاضَةَ ...........",
      "opts": [
        "يَحْفَظْ جِسْمَهُ مِنَ مَرَضِ",
        "فَحَفِظَ جِسْمَهُ",
        "لَحَفِظَ جِسْمَهُ",
        "يَحْفَظُ جِسْمَهُ"
      ],
      "correct": 0,
      "izoh": "Toʻgʻri javob: «يَحْفَظْ جِسْمَهُ مِنَ مَرَضِ»."
    },
    {
      "q": "Boʻsh joyga mos soʻzni tanlang:\nإِنْ زُرْتُمْ مَدِينَتِي ...........",
      "opts": [
        "تُسَرُّونَ",
        "فَسُرِرْتُمْ",
        "تُسَرُّوا",
        "لَتُسَرُّوا"
      ],
      "correct": 2,
      "izoh": "Toʻgʻri javob: «تُسَرُّوا»."
    },
    {
      "q": "Boʻsh joyga mos soʻzni tanlang:\nمَنْ يَقْرَأْ كُتُبًا مُفِيدَةً ...........",
      "opts": [
        "يَزْدَدْ عِلْمُهُ",
        "فَيَزْدَادُ عِلْمُهُ",
        "يَزْدَادُ عِلْمُهُ",
        "لَازْدَادَ عِلْمُهُ"
      ],
      "correct": 0,
      "izoh": "Toʻgʻri javob: «يَزْدَدْ عِلْمُهُ»."
    },
    {
      "q": "Boʻsh joyga mos soʻzni tanlang:\nإِذَا شَعَرْتَ بِأَلَمٍ فِي أَسْنَانِكَ ...........",
      "opts": [
        "لَذَهَبْتَ إِلَى الطَّبِيبِ",
        "يَذْهَبُ إِلَى الطَّبِيبِ",
        "تَذْهَبْ إِلَى الطَّبِيبِ",
        "فَاذْهَبْ إِلَى الطَّبِيبِ"
      ],
      "correct": 3,
      "izoh": "Toʻgʻri javob: «فَاذْهَبْ إِلَى الطَّبِيبِ»."
    },
    {
      "q": "Boʻsh joyga mos soʻzni tanlang:\nمَنْ يَأْكُلْ كَثِيرًا ...........",
      "opts": [
        "لَمَرِضَ",
        "يَمْرَضُ",
        "يَمْرَضْ",
        "فَيَمْرَضُ"
      ],
      "correct": 2,
      "izoh": "Toʻgʻri javob: «يَمْرَضْ»."
    },
    {
      "q": "Boʻsh joyga mos soʻzni tanlang:\nلَوْ عَرَفْتُ أَنَّكَ فَقِيرٌ ...........",
      "opts": [
        "سَاعَدْتُكَ",
        "لَسَاعَدْتُكَ",
        "أُسَاعِدْكَ",
        "فَأُسَاعِدُكَ"
      ],
      "correct": 1,
      "izoh": "Toʻgʻri javob: «لَسَاعَدْتُكَ»."
    },
    {
      "q": "Boʻsh joyga mos soʻzni tanlang:\nإِذَا فَتَحْتَ الهَاتِفَ لِتَصَفُّحِ الإِنْتِرْنِتِ، ...........",
      "opts": [
        "يَقُولُ أَبِي: لَا تَسْتَخْدِمْهُ كَثِيرًا فَهُوَ ضَارٌّ",
        "فَلَنْ يَبْقَى إِنْسَانٌ فَقِيرٌ",
        "لَمَا اسْتَطَعْنَا أَنْ نَتَوَاصَلَ",
        "لَمْ نَجِدْ تَلَوُّثًا حَوْلَنَا"
      ],
      "correct": 0,
      "izoh": "Toʻgʻri javob: «يَقُولُ أَبِي: لَا تَسْتَخْدِمْهُ كَثِيرًا فَهُوَ ضَارٌّ»."
    },
    {
      "q": "Boʻsh joyga mos soʻzni tanlang:\nلَوْ حَافَظَ كُلُّ إِنْسَانٍ عَلَى النَّظَافَةِ ...........",
      "opts": [
        "فَسَتَتَأَخَّرُ عَنْ مَوْعِدِ اجْتِمَاعِ اليَوْمِ",
        "لَمْ نَجِدْ تَلَوُّثًا حَوْلَنَا",
        "يُصْبِحْ جِسْمُهُ قَوِيًّا",
        "فَلَنْ يَبْقَى إِنْسَانٌ فَقِيرٌ"
      ],
      "correct": 1,
      "izoh": "Toʻgʻri javob: «لَمْ نَجِدْ تَلَوُّثًا حَوْلَنَا»."
    },
    {
      "q": "Boʻsh joyga mos soʻzni tanlang:\nإِنْ لَمْ تَصِلِ الطَّائِرَةُ فِي مَوْعِدِهَا المُحَدَّدِ ...........",
      "opts": [
        "يُصْبِحْ جِسْمُهُ قَوِيًّا",
        "لَمْ نَجِدْ تَلَوُّثًا حَوْلَنَا",
        "لَمَا اسْتَطَعْنَا أَنْ نَتَوَاصَلَ",
        "فَسَتَتَأَخَّرُ عَنْ مَوْعِدِ اجْتِمَاعِ اليَوْمِ"
      ],
      "correct": 3,
      "izoh": "Toʻgʻri javob: «فَسَتَتَأَخَّرُ عَنْ مَوْعِدِ اجْتِمَاعِ اليَوْمِ»."
    },
    {
      "q": "Boʻsh joyga mos soʻzni tanlang:\nمَنْ يُمَارِسِ الرِّيَاضَةَ بِانْتِظَامٍ ...........",
      "opts": [
        "لَمْ نَجِدْ تَلَوُّثًا حَوْلَنَا",
        "يُصْبِحْ جِسْمُهُ قَوِيًّا وَسَلِيمًا مِنْ كَثِيرٍ مِنَ الأَمْرَاضِ",
        "فَلَنْ يَبْقَى إِنْسَانٌ فَقِيرٌ",
        "فَسَتَتَأَخَّرُ عَنْ مَوْعِدِ اجْتِمَاعِ اليَوْمِ"
      ],
      "correct": 1,
      "izoh": "Toʻgʻri javob: «يُصْبِحْ جِسْمُهُ قَوِيًّا وَسَلِيمًا مِنْ كَثِيرٍ مِنَ الأَمْرَاضِ»."
    },
    {
      "q": "Boʻsh joyga mos soʻzni tanlang:\nلَوْ لَمْ تَكُنِ الهَوَاتِفُ الحَدِيثَةُ مَوْجُودَةً ...........",
      "opts": [
        "لَمَا اسْتَطَعْنَا أَنْ نَتَوَاصَلَ وَنَحْنُ بَعِيدُونَ عَنْ بَعْضِنَا البَعْضِ",
        "لَمْ نَجِدْ تَلَوُّثًا حَوْلَنَا",
        "يُصْبِحْ جِسْمُهُ قَوِيًّا",
        "فَلَنْ يَبْقَى إِنْسَانٌ فَقِيرٌ"
      ],
      "correct": 0,
      "izoh": "Toʻgʻri javob: «لَمَا اسْتَطَعْنَا أَنْ نَتَوَاصَلَ وَنَحْنُ بَعِيدُونَ عَنْ بَعْضِنَا البَعْضِ»."
    },
    {
      "q": "Boʻsh joyga mos soʻzni tanlang:\nإِذَا أَعْطَى كُلُّ الأَغْنِيَاءِ زَكَاةَ مَالِهِمْ دُونَ نَقْصٍ ...........",
      "opts": [
        "فَسَتَتَأَخَّرُ عَنْ مَوْعِدِ اجْتِمَاعِ اليَوْمِ",
        "لَمَا اسْتَطَعْنَا أَنْ نَتَوَاصَلَ",
        "فَلَنْ يَبْقَى إِنْسَانٌ فَقِيرٌ فِي العَالَمِ",
        "لَمْ نَجِدْ تَلَوُّثًا حَوْلَنَا"
      ],
      "correct": 2,
      "izoh": "Toʻgʻri javob: «فَلَنْ يَبْقَى إِنْسَانٌ فَقِيرٌ فِي العَالَمِ»."
    },
    {
      "q": "E'rob qoidalariga ko'ra to'g'ri fe'l shaklini tanlang:\nيُرِيدُ أَخِي أَنْ ........... بَيْتًا جَدِيدًا.",
      "opts": [
        "يَبْنُونَ",
        "يَبْنِيَ",
        "يَبْنِ",
        "يَبْنِي"
      ],
      "correct": 1,
      "izoh": "Toʻgʻri javob: «يَبْنِيَ»."
    },
    {
      "q": "Boʻsh joyga mos soʻzni tanlang:\nاِبْنُ عَمِّي لَنْ ........... عِنْدَنَا اللَّيْلَةَ.",
      "opts": [
        "يَبْقَيَ",
        "يَبْقَ",
        "يَبْقَى",
        "يَبْقَوْنَ"
      ],
      "correct": 2,
      "izoh": "Toʻgʻri javob: «يَبْقَى»."
    },
    {
      "q": "Boʻsh joyga mos soʻzni tanlang:\n........... عَائِلَتِي العُطْلَةَ عَلَى شَاطِئِ البَحْرِ.",
      "opts": [
        "تَمْضِيَ",
        "تَمْضِي",
        "تَمْضِينَ",
        "تَمْضِ"
      ],
      "correct": 1,
      "izoh": "Toʻgʻri javob: «تَمْضِي»."
    },
    {
      "q": "Boʻsh joyga mos soʻzni tanlang:\nلِـ ........... مِنَ النَّوْمِ مُبَكِّرًا يَا فَادِي.",
      "opts": [
        "تَصْحُوَ",
        "تَصْحُو",
        "تَصْحُونَ",
        "تَصْحُ"
      ],
      "correct": 3,
      "izoh": "Toʻgʻri javob: «تَصْحُ»."
    },
    {
      "q": "Boʻsh joyga mos soʻzni tanlang:\nنَحْنُ ........... الأَغْنَامَ وَالأَبْقَارَ خَارِجَ القَرْيَةِ.",
      "opts": [
        "نَرْعَ",
        "نَرْعَى",
        "نَرْعَيَ",
        "نَرْعَوْنَ"
      ],
      "correct": 1,
      "izoh": "Toʻgʻri javob: «نَرْعَى»."
    },
    {
      "q": "Boʻsh joyga mos soʻzni tanlang:\nذَهَبْتُ إِلَى السُّوقِ لِـ ........... مَا أَحْتَاجُ إِلَيْهِ.",
      "opts": [
        "أَشْتَرِي",
        "نَشْتَرِي",
        "أَشْتَرِ",
        "أَشْتَرِيَ"
      ],
      "correct": 3,
      "izoh": "Toʻgʻri javob: «أَشْتَرِيَ»."
    },
    {
      "q": "Boʻsh joyga mos soʻzni tanlang:\nالخَشَبُ ........... عَلَى المَاءِ.",
      "opts": [
        "يَطْفُوَ",
        "يَطْفُونَ",
        "يَطْفُ",
        "يَطْفُو"
      ],
      "correct": 3,
      "izoh": "Toʻgʻri javob: «يَطْفُو»."
    },
    {
      "q": "Boʻsh joyga mos soʻzni tanlang:\nلَا ........... القُمَامَةَ مِنَ النَّافِذَةِ.",
      "opts": [
        "تَرْمِي",
        "تَرْمِ",
        "تَرْمِيَ",
        "تَرْمُونَ"
      ],
      "correct": 1,
      "izoh": "Toʻgʻri javob: «تَرْمِ»."
    },
    {
      "q": "Berilgan gapning to'g'ri ta'kidlangan (مؤكدة) shaklini tanlang.",
      "opts": [
        "لَقَدْ لَا تَتَصَرَّفْ بِشَكْلٍ سَيِّئٍ مَعَ أَبَوَيْكَ",
        "إِنْ لَا تَتَصَرَّفْ بِشَكْلٍ سَيِّئٍ مَعَ أَبَوَيْكَ",
        "لَا تَتَصَرَّفَنَّ بِشَكْلٍ سَيِّئٍ مَعَ أَبَوَيْكَ",
        "لَا تَتَصَرَّفُ بِشَكْلٍ سَيِّئٍ مَعَ أَبَوَيْكَ"
      ],
      "correct": 2,
      "izoh": "Toʻgʻri javob: «لَا تَتَصَرَّفَنَّ بِشَكْلٍ سَيِّئٍ مَعَ أَبَوَيْكَ»."
    },
    {
      "q": "Toʻgʻri javobni tanlang:\n(إِخْلَاصُ كُلِّ شَخْصٍ فِي عَمَلِهِ يُحَقِّقُ لِلْأُمَّةِ أَهْدَافَهَا)",
      "opts": [
        "لَوْ إِخْلَاصُ كُلِّ شَخْصٍ فِي عَمَلِهِ يُحَقِّقُ لِلْأُمَّةِ أَهْدَافَهَا",
        "إِنَّ إِخْلَاصَ كُلِّ شَخْصٍ فِي عَمَلِهِ يُحَقِّقُ لِلْأُمَّةِ أَهْدَافَهَا",
        "إِخْلَاصَنَّ كُلِّ شَخْصٍ فِي عَمَلِهِ يُحَقِّقُ لِلْأُمَّةِ أَهْدَافَهَا",
        "قَدْ إِخْلَاصُ كُلِّ شَخْصٍ فِي عَمَلِهِ يُحَقِّقُ لِلْأُمَّةِ أَهْدَافَهَا"
      ],
      "correct": 1,
      "izoh": "Toʻgʻri javob: «إِنَّ إِخْلَاصَ كُلِّ شَخْصٍ فِي عَمَلِهِ يُحَقِّقُ لِلْأُمَّةِ أَهْدَافَهَا»."
    },
    {
      "q": "Toʻgʻri javobni tanlang:\n(سَاعِدْ مَنْ يَحْتَاجُ كَيْ يَحْتَرِمَكَ النَّاسُ)",
      "opts": [
        "إِنَّ سَاعَدَ مَنْ يَحْتَاجُ كَيْ يَحْتَرِمَكَ النَّاسُ",
        "سَاعِدَنَّ مَنْ يَحْتَاجُ كَيْ يَحْتَرِمَكَ النَّاسُ",
        "لَسَوْفَ سَاعَدَ مَنْ يَحْتَاجُ كَيْ يَحْتَرِمَكَ النَّاسُ",
        "قَدْ سَاعِدْ مَنْ يَحْتَاجُ كَيْ يَحْتَرِمَكَ النَّاسُ"
      ],
      "correct": 1,
      "izoh": "Toʻgʻri javob: «سَاعِدَنَّ مَنْ يَحْتَاجُ كَيْ يَحْتَرِمَكَ النَّاسُ»."
    },
    {
      "q": "Toʻgʻri javobni tanlang:\n(لا يُؤْمِنُ أَحَدُكُمْ حَتَّى يُحِبَّ لِأَخِيهِ مَا يُحِبُّ لِنَفْسِهِ)",
      "opts": [
        "قَدْ لَا يُؤْمِنُ أَحَدُكُمْ حَتَّى يُحِبَّ لِأَخِيهِ مَا يُحِبُّ لِنَفْسِهِ",
        "لَا يُؤْمِنَنَّ أَحَدُكُمْ حَتَّى يُحِبَّ لِأَخِيهِ مَا يُحِبُّ لِنَفْسِهِ",
        "وَاللهِ لَا يُؤْمِنُ أَحَدُكُمْ حَتَّى يُحِبَّ لِأَخِيهِ مَا يُحِبُّ لِنَفْسِهِ",
        "إِنَّ لَا يُؤْمِنُ أَحَدُكُمْ حَتَّى يُحِبَّ لِأَخِيهِ مَا يُحِبُّ لِنَفْسِهِ"
      ],
      "correct": 2,
      "izoh": "Toʻgʻri javob: «وَاللهِ لَا يُؤْمِنُ أَحَدُكُمْ حَتَّى يُحِبَّ لِأَخِيهِ مَا يُحِبُّ لِنَفْسِهِ»."
    },
    {
      "q": "Toʻgʻri javobni tanlang:\n(اشْتُهِرَ أَشْعَبُ بِالطَّفِيلِيَّةِ)",
      "opts": [
        "إِنَّ اشْتُهِرَ أَشْعَبُ بِالطَّفِيلِيَّةِ",
        "اشْتُهِرَنَّ أَشْعَبُ بِالطَّفِيلِيَّةِ",
        "قَدِ اشْتُهِرَ أَشْعَبُ بِالطَّفِيلِيَّةِ",
        "لَعَلَّ اشْتُهِرَ أَشْعَبُ بِالطَّفِيلِيَّةِ"
      ],
      "correct": 2,
      "izoh": "Toʻgʻri javob: «قَدِ اشْتُهِرَ أَشْعَبُ بِالطَّفِيلِيَّةِ»."
    },
    {
      "q": "Toʻgʻri javobni tanlang:\n(اِرْجِعْ إِلَى البَيْتِ قَبْلَ أَنْ يَتَأَخَّرَ الوَقْتُ يَا بُنَيَّ)",
      "opts": [
        "قَدْ اِرْجِعْ إِلَى البَيْتِ قَبْلَ أَنْ يَتَأَخَّرَ الوَقْتُ يَا بُنَيَّ",
        "إِنَّ اِرْجِعْ إِلَى البَيْتِ قَبْلَ أَنْ يَتَأَخَّرَ الوَقْتُ يَا بُنَيَّ",
        "لَوْ اِرْجِعْ إِلَى البَيْتِ قَبْلَ أَنْ يَتَأَخَّرَ الوَقْتُ يَا بُنَيَّ",
        "اِرْجِعَنَّ إِلَى البَيْتِ قَبْلَ أَنْ يَتَأَخَّرَ الوَقْتُ يَا بُنَيَّ"
      ],
      "correct": 3,
      "izoh": "Toʻgʻri javob: «اِرْجِعَنَّ إِلَى البَيْتِ قَبْلَ أَنْ يَتَأَخَّرَ الوَقْتُ يَا بُنَيَّ»."
    },
    {
      "q": "Toʻgʻri javobni tanlang:\n(السَّيَّارَةُ سَرِيعَةٌ، لَكِنَّ القِطَارَ أَسْرَعُ مِنْهَا)",
      "opts": [
        "السَّيَّارَتَنَّ سَرِيعَةٌ، لَكِنَّ القِطَارَ أَسْرَعُ مِنْهَا",
        "إِنَّ السَّيَّارَةَ سَرِيعَةٌ، لَكِنَّ القِطَارَ أَسْرَعُ مِنْهَا",
        "لَوْ السَّيَّارَةُ سَرِيعَةٌ، لَكِنَّ القِطَارَ أَسْرَعُ مِنْهَا",
        "قَدِ السَّيَّارَةُ سَرِيعَةٌ، لَكِنَّ القِطَارَ أَسْرَعُ مِنْهَا"
      ],
      "correct": 1,
      "izoh": "Toʻgʻri javob: «إِنَّ السَّيَّارَةَ سَرِيعَةٌ، لَكِنَّ القِطَارَ أَسْرَعُ مِنْهَا»."
    },
    {
      "q": "Toʻgʻri javobni tanlang:\n(أَنَا رَأَيْتُ الطُّلَّابَ يَخْرُجُونَ مِنَ الصَّفِّ)",
      "opts": [
        "أَنَا رَأَيْتَنَّ الطُّلَّابَ يَخْرُجُونَ مِنَ الصَّفِّ",
        "لَوْ أَنَا رَأَيْتُ الطُّلَّابَ يَخْرُجُونَ مِنَ الصَّفِّ",
        "أَنَا لَقَدْ رَأَيْتُ الطُّلَّابَ يَخْرُجُونَ مِنَ الصَّفِّ",
        "إِنَّ أَنَا رَأَيْتُ الطُّلَّابَ يَخْرُجُونَ مِنَ الصَّفِّ"
      ],
      "correct": 2,
      "izoh": "Toʻgʻri javob: «أَنَا لَقَدْ رَأَيْتُ الطُّلَّابَ يَخْرُجُونَ مِنَ الصَّفِّ»."
    },
    {
      "q": "Toʻgʻri javobni tanlang:\n(أَكْرِمْ ضُيُوفَكَ حِينَ يَزُورُونَكَ)",
      "opts": [
        "أَكْرِمَنَّ ضُيُوفَكَ حِينَ يَزُورُونَكَ",
        "قَدْ أَكْرِمْ ضُيُوفَكَ حِينَ يَزُورُونَكَ",
        "إِنَّ أَكْرِمْ ضُيُوفَكَ حِينَ يَزُورُونَكَ",
        "سَوْفَ أَكْرِمْ ضُيُوفَكَ حِينَ يَزُورُونَكَ"
      ],
      "correct": 0,
      "izoh": "Toʻgʻri javob: «أَكْرِمَنَّ ضُيُوفَكَ حِينَ يَزُورُونَكَ»."
    },
    {
      "q": "Toʻgʻri javobni tanlang:\n(يَصْعَدُ مَحْمُودٌ إِلَى الطَّابِقِ الخَامِسِ)",
      "opts": [
        "وَاللهِ لَيَصْعَدَنَّ مَحْمُودٌ إِلَى الطَّابِقِ الخَامِسِ",
        "إِنَّ يَصْعَدُ مَحْمُودٌ إِلَى الطَّابِقِ الخَامِسِ",
        "لَوْ يَصْعَدُ مَحْمُودٌ إِلَى الطَّابِقِ الخَامِسِ",
        "يَصْعَدْ مَحْمُودٌ إِلَى الطَّابِقِ الخَامِسِ"
      ],
      "correct": 0,
      "izoh": "Toʻgʻri javob: «وَاللهِ لَيَصْعَدَنَّ مَحْمُودٌ إِلَى الطَّابِقِ الخَامِسِ»."
    }
  ]
}