{
  "title": "Mufradot — C1 3-dars",
  "otish": 80,
  "vaqt": 20,
  "questions": [
    {
      "q": "«نُقُودٌ» — to'g'ri tarjimasi?",
      "opts": [
        "norozilik bildirma, \"uf\" dema",
        "to'qnashdi",
        "pullar",
        "qadam"
      ],
      "correct": 2,
      "izoh": "pullar = نُقُودٌ"
    },
    {
      "q": "«cho'milasan» — to'g'ri arabcha tarjimasi?",
      "opts": [
        "تَسْتَحِمُّ",
        "مُشْتَاقٌ",
        "صَارُوخٌ",
        "مُشْتَقٌّ"
      ],
      "correct": 0,
      "izoh": "cho'milasan = تَسْتَحِمُّ"
    },
    {
      "q": "«رِضَا» — to'g'ri tarjimasi?",
      "opts": [
        "duolar",
        "kashf qilasan, bilib olasan",
        "senga barcha yo'llarni tekislayman (tayyorlayman)",
        "rozi bo'lish, rozilik"
      ],
      "correct": 3,
      "izoh": "rozi bo'lish, rozilik = رِضَا"
    },
    {
      "q": "«(gapni) bo'lasan, xalaqit berasan» — to'g'ri arabcha tarjimasi?",
      "opts": [
        "يَدْنُو",
        "تَتَحَلَّى",
        "تُقَاطِعُ",
        "اصْطَدَمَ"
      ],
      "correct": 2,
      "izoh": "(gapni) bo'lasan, xalaqit berasan = تُقَاطِعُ"
    },
    {
      "q": "«نُخَزِّنُ» — to'g'ri tarjimasi?",
      "opts": [
        "saqlaymiz, zaxira qilamiz",
        "menga ber, taqdim et",
        "mikroskop",
        "raketa"
      ],
      "correct": 0,
      "izoh": "saqlaymiz, zaxira qilamiz = نُخَزِّنُ"
    },
    {
      "q": "«diqqat bilan quloq soldi» — to'g'ri arabcha tarjimasi?",
      "opts": [
        "بَلَغَ مِنَ الكِبَرِ عَتِيًّا",
        "شِرَاعٌ",
        "نُخَزِّنُ",
        "أَنْصَتَ"
      ],
      "correct": 3,
      "izoh": "diqqat bilan quloq soldi = أَنْصَتَ"
    },
    {
      "q": "«عَجُوزٌ» — to'g'ri tarjimasi?",
      "opts": [
        "masxaralovchi (kesatiq) tabassum bilan",
        "cho'milasan",
        "qari, keksa",
        "o'zim yolg'iz (mustaqil ravishda)"
      ],
      "correct": 2,
      "izoh": "qari, keksa = عَجُوزٌ"
    },
    {
      "q": "«g'amxo'rlik, qarab turish» — to'g'ri arabcha tarjimasi?",
      "opts": [
        "يَدْنُو",
        "رِعَايَةٌ",
        "تَتَّصِفُ",
        "بِطَاقَاتٌ"
      ],
      "correct": 1,
      "izoh": "g'amxo'rlik, qarab turish = رِعَايَةٌ"
    },
    {
      "q": "«يَجُوزُ» — to'g'ri tarjimasi?",
      "opts": [
        "ruxsat etiladi, joiz bo'ladi",
        "band bo'lasan, chalg'iysan",
        "yasalgan, kelib chiqqan so'z (grammatikada)",
        "kartalar (plastik, vizitka)"
      ],
      "correct": 0,
      "izoh": "ruxsat etiladi, joiz bo'ladi = يَجُوزُ"
    },
    {
      "q": "«qadam» — to'g'ri arabcha tarjimasi?",
      "opts": [
        "اصْطَدَمَ",
        "امْنَحْنِي",
        "خُطْوَةٌ",
        "تَتَّصِفُ"
      ],
      "correct": 2,
      "izoh": "qadam = خُطْوَةٌ"
    },
    {
      "q": "«اصْطَدَمَ» — to'g'ri tarjimasi?",
      "opts": [
        "takrorlash",
        "masxaralovchi (kesatiq) tabassum bilan",
        "diqqat bilan tinglash",
        "to'qnashdi"
      ],
      "correct": 3,
      "izoh": "to'qnashdi = اصْطَدَمَ"
    },
    {
      "q": "«senga barcha yo'llarni tekislayman (tayyorlayman)» — to'g'ri arabcha tarjimasi?",
      "opts": [
        "بِابْتِسَامَةٍ سَاخِرَةٍ",
        "عُقُوقُ الوَالِدَيْنِ",
        "أُمَهِّدُ لَكَ الطُّرُقَ",
        "طَلِيقٌ"
      ],
      "correct": 2,
      "izoh": "senga barcha yo'llarni tekislayman (tayyorlayman) = أُمَهِّدُ لَكَ الطُّرُقَ"
    },
    {
      "q": "«مُشْتَاقٌ» — to'g'ri tarjimasi?",
      "opts": [
        "(gapni) bo'lasan, xalaqit berasan",
        "hayotga yuzlanasan (hayot qiyinchiliklariga qarshi turasan)",
        "(she'r, qo'shiq) aytish",
        "mushtoq, sog'ingan"
      ],
      "correct": 3,
      "izoh": "mushtoq, sog'ingan = مُشْتَاقٌ"
    },
    {
      "q": "«yaqinlashadi» — to'g'ri arabcha tarjimasi?",
      "opts": [
        "تَتَحَلَّى",
        "نَسْتَيْقِظُ",
        "تُقَاطِعُ",
        "يَدْنُو"
      ],
      "correct": 3,
      "izoh": "yaqinlashadi = يَدْنُو"
    },
    {
      "q": "«مِصْبَاحٌ» — to'g'ri tarjimasi?",
      "opts": [
        "(she'r, qo'shiq) aytish",
        "kashf qilasan, bilib olasan",
        "chiroq",
        "kiyimlar"
      ],
      "correct": 2,
      "izoh": "chiroq = مِصْبَاحٌ"
    },
    {
      "q": "«nafaqaga chiqdi» — to'g'ri arabcha tarjimasi?",
      "opts": [
        "رِضَا",
        "تَكْتَشِفُ",
        "تَقَاعَدَ",
        "مِجْهَرٌ"
      ],
      "correct": 2,
      "izoh": "nafaqaga chiqdi = تَقَاعَدَ"
    },
    {
      "q": "«بَلَغَ مِنَ الكِبَرِ عَتِيًّا» — to'g'ri tarjimasi?",
      "opts": [
        "kashf qilasan, bilib olasan",
        "siyrat, tarjimai hol",
        "senga barcha yo'llarni tekislayman (tayyorlayman)",
        "keksayib, qarib qolgan"
      ],
      "correct": 3,
      "izoh": "keksayib, qarib qolgan = بَلَغَ مِنَ الكِبَرِ عَتِيًّا"
    },
    {
      "q": "«yelkan» — to'g'ri arabcha tarjimasi?",
      "opts": [
        "عَجُوزٌ",
        "تَنْشَغِلُ",
        "تَكْرَارٌ",
        "شِرَاعٌ"
      ],
      "correct": 3,
      "izoh": "yelkan = شِرَاعٌ"
    },
    {
      "q": "«خَضْرَاوَاتٌ» — to'g'ri tarjimasi?",
      "opts": [
        "takrorlash",
        "sabzavotlar",
        "bolta",
        "zilzila"
      ],
      "correct": 1,
      "izoh": "sabzavotlar = خَضْرَاوَاتٌ"
    },
    {
      "q": "«tokcha (chiroq qo'yiladigan)» — to'g'ri arabcha tarjimasi?",
      "opts": [
        "آلَةٌ",
        "اصْطَدَمَ",
        "مِشْكَاةٌ",
        "مِجْهَرٌ"
      ],
      "correct": 2,
      "izoh": "tokcha (chiroq qo'yiladigan) = مِشْكَاةٌ"
    }
  ]
}